[
    {
        "id": 1,
        "first_name": "Deeanne",
        "last_name": "Lalevee"
    },
    {
        "id": 2,
        "first_name": "Kassie",
        "last_name": "Stubbes"
    },
    {
        "id": 3,
        "first_name": "Halli",
        "last_name": "Trench"
    },
    {
        "id": 4,
        "first_name": "Zorana",
        "last_name": "Regitz"
    },
    {
        "id": 5,
        "first_name": "Titos",
        "last_name": "Boagey"
    },
    {
        "id": 6,
        "first_name": "Clerc",
        "last_name": "de Chastelain"
    },
    {
        "id": 7,
        "first_name": "Katharina",
        "last_name": "Cathesyed"
    },
    {
        "id": 8,
        "first_name": "Wilden",
        "last_name": "Kytley"
    },
    {
        "id": 9,
        "first_name": "April",
        "last_name": "MacNamara"
    },
    {
        "id": 10,
        "first_name": "Vladimir",
        "last_name": "Dike"
    },
    {
        "id": 11,
        "first_name": "Gerianne",
        "last_name": "Garham"
    },
    {
        "id": 12,
        "first_name": "Sarah",
        "last_name": "Senton"
    },
    {
        "id": 13,
        "first_name": "Larine",
        "last_name": "Reidshaw"
    },
    {
        "id": 14,
        "first_name": "Marguerite",
        "last_name": "Bows"
    },
    {
        "id": 15,
        "first_name": "Danie",
        "last_name": "Walenta"
    },
    {
        "id": 16,
        "first_name": "Timofei",
        "last_name": "Fawks"
    },
    {
        "id": 17,
        "first_name": "Edik",
        "last_name": "Schaffler"
    },
    {
        "id": 18,
        "first_name": "Denis",
        "last_name": "Hubert"
    },
    {
        "id": 19,
        "first_name": "Regan",
        "last_name": "Pleace"
    },
    {
        "id": 20,
        "first_name": "Cleveland",
        "last_name": "Kilmartin"
    },
    {
        "id": 21,
        "first_name": "Gilles",
        "last_name": "Verryan"
    },
    {
        "id": 22,
        "first_name": "Katherina",
        "last_name": "Bick"
    },
    {
        "id": 23,
        "first_name": "Mendie",
        "last_name": "Sterricks"
    },
    {
        "id": 24,
        "first_name": "Jolie",
        "last_name": "Vuitton"
    },
    {
        "id": 25,
        "first_name": "Philipa",
        "last_name": "Bellward"
    },
    {
        "id": 26,
        "first_name": "Laraine",
        "last_name": "Karolovsky"
    },
    {
        "id": 27,
        "first_name": "Amble",
        "last_name": "Ivanyutin"
    },
    {
        "id": 28,
        "first_name": "Vivienne",
        "last_name": "Flower"
    },
    {
        "id": 29,
        "first_name": "Blondy",
        "last_name": "Jewiss"
    },
    {
        "id": 30,
        "first_name": "Oona",
        "last_name": "Dunckley"
    },
    {
        "id": 31,
        "first_name": "Olva",
        "last_name": "Chappell"
    },
    {
        "id": 32,
        "first_name": "Penn",
        "last_name": "Rentenbeck"
    },
    {
        "id": 33,
        "first_name": "Gilbertina",
        "last_name": "Benito"
    },
    {
        "id": 34,
        "first_name": "Raynard",
        "last_name": "Pipkin"
    },
    {
        "id": 35,
        "first_name": "Rosabelle",
        "last_name": "Somerscales"
    },
    {
        "id": 36,
        "first_name": "Jeanie",
        "last_name": "Mallabone"
    },
    {
        "id": 37,
        "first_name": "Georgianna",
        "last_name": "Lowde"
    },
    {
        "id": 38,
        "first_name": "Sybyl",
        "last_name": "Collimore"
    },
    {
        "id": 39,
        "first_name": "Zulema",
        "last_name": "Chate"
    },
    {
        "id": 40,
        "first_name": "Lolita",
        "last_name": "Dauncey"
    },
    {
        "id": 41,
        "first_name": "Byran",
        "last_name": "Fulle"
    },
    {
        "id": 42,
        "first_name": "Susanna",
        "last_name": "Kleint"
    },
    {
        "id": 43,
        "first_name": "Cally",
        "last_name": "Havard"
    },
    {
        "id": 44,
        "first_name": "Falkner",
        "last_name": "Feasby"
    },
    {
        "id": 45,
        "first_name": "Abbot",
        "last_name": "St Clair"
    },
    {
        "id": 46,
        "first_name": "Bertrand",
        "last_name": "Attwooll"
    },
    {
        "id": 47,
        "first_name": "Romy",
        "last_name": "Hazel"
    },
    {
        "id": 48,
        "first_name": "Prudy",
        "last_name": "Perroni"
    },
    {
        "id": 49,
        "first_name": "Umeko",
        "last_name": "Mutter"
    },
    {
        "id": 50,
        "first_name": "Tawsha",
        "last_name": "Simmon"
    },
    {
        "id": 51,
        "first_name": "Merv",
        "last_name": "Throssell"
    },
    {
        "id": 52,
        "first_name": "Hilda",
        "last_name": "Potell"
    },
    {
        "id": 53,
        "first_name": "Ernestine",
        "last_name": "Kirmond"
    },
    {
        "id": 54,
        "first_name": "Gray",
        "last_name": "Press"
    },
    {
        "id": 55,
        "first_name": "Matti",
        "last_name": "Zecchii"
    },
    {
        "id": 56,
        "first_name": "Burgess",
        "last_name": "Griffith"
    },
    {
        "id": 57,
        "first_name": "Onfre",
        "last_name": "De Hooch"
    },
    {
        "id": 58,
        "first_name": "Annette",
        "last_name": "Rocca"
    },
    {
        "id": 59,
        "first_name": "Bellanca",
        "last_name": "Allsebrook"
    },
    {
        "id": 60,
        "first_name": "Benedicto",
        "last_name": "Bowell"
    },
    {
        "id": 61,
        "first_name": "Adelaida",
        "last_name": "Rollin"
    },
    {
        "id": 62,
        "first_name": "Dory",
        "last_name": "Kenion"
    },
    {
        "id": 63,
        "first_name": "Tremaine",
        "last_name": "Rothschild"
    },
    {
        "id": 64,
        "first_name": "Lorens",
        "last_name": "Byrne"
    },
    {
        "id": 65,
        "first_name": "Clary",
        "last_name": "Badger"
    },
    {
        "id": 66,
        "first_name": "Nicko",
        "last_name": "Kyberd"
    },
    {
        "id": 67,
        "first_name": "Colin",
        "last_name": "Beddo"
    },
    {
        "id": 68,
        "first_name": "Emylee",
        "last_name": "Dunster"
    },
    {
        "id": 69,
        "first_name": "Alva",
        "last_name": "Flatman"
    },
    {
        "id": 70,
        "first_name": "Olivia",
        "last_name": "Sainte Paul"
    },
    {
        "id": 71,
        "first_name": "Brandie",
        "last_name": "Abelwhite"
    },
    {
        "id": 72,
        "first_name": "Phyllis",
        "last_name": "McReynolds"
    },
    {
        "id": 73,
        "first_name": "Sanford",
        "last_name": "Rathe"
    },
    {
        "id": 74,
        "first_name": "Ciel",
        "last_name": "Skinn"
    },
    {
        "id": 75,
        "first_name": "Sly",
        "last_name": "Shortin"
    },
    {
        "id": 76,
        "first_name": "Christos",
        "last_name": "Fullard"
    },
    {
        "id": 77,
        "first_name": "Beltran",
        "last_name": "Blackborow"
    },
    {
        "id": 78,
        "first_name": "Malina",
        "last_name": "Hanmore"
    },
    {
        "id": 79,
        "first_name": "Rebe",
        "last_name": "Caunter"
    },
    {
        "id": 80,
        "first_name": "Myrvyn",
        "last_name": "McLeman"
    },
    {
        "id": 81,
        "first_name": "Shayne",
        "last_name": "Craine"
    },
    {
        "id": 82,
        "first_name": "Marchelle",
        "last_name": "Semonin"
    },
    {
        "id": 83,
        "first_name": "Augusto",
        "last_name": "Tomowicz"
    },
    {
        "id": 84,
        "first_name": "Biddy",
        "last_name": "Ricciardelli"
    },
    {
        "id": 85,
        "first_name": "Corbie",
        "last_name": "Kenlin"
    },
    {
        "id": 86,
        "first_name": "Christalle",
        "last_name": "McLaughlin"
    },
    {
        "id": 87,
        "first_name": "Ric",
        "last_name": "Lasselle"
    },
    {
        "id": 88,
        "first_name": "Werner",
        "last_name": "Peacher"
    },
    {
        "id": 89,
        "first_name": "Keith",
        "last_name": "Corking"
    },
    {
        "id": 90,
        "first_name": "Myles",
        "last_name": "Hatcher"
    },
    {
        "id": 91,
        "first_name": "Orren",
        "last_name": "Wagg"
    },
    {
        "id": 92,
        "first_name": "Daryn",
        "last_name": "Corpe"
    },
    {
        "id": 93,
        "first_name": "Carie",
        "last_name": "Cushion"
    },
    {
        "id": 94,
        "first_name": "Dasha",
        "last_name": "McIlrath"
    },
    {
        "id": 95,
        "first_name": "Teresita",
        "last_name": "Fiddyment"
    },
    {
        "id": 96,
        "first_name": "Aluino",
        "last_name": "Scanlon"
    },
    {
        "id": 97,
        "first_name": "Verene",
        "last_name": "Caroli"
    },
    {
        "id": 98,
        "first_name": "Gilligan",
        "last_name": "Assante"
    },
    {
        "id": 99,
        "first_name": "Renato",
        "last_name": "Barnicott"
    },
    {
        "id": 100,
        "first_name": "Jud",
        "last_name": "Sibbald"
    },
    {
        "id": 101,
        "first_name": "Kerwinn",
        "last_name": "Wollacott"
    },
    {
        "id": 102,
        "first_name": "Kiley",
        "last_name": "Jorczyk"
    },
    {
        "id": 103,
        "first_name": "Marie",
        "last_name": "Sessions"
    },
    {
        "id": 104,
        "first_name": "Fabe",
        "last_name": "Raithmill"
    },
    {
        "id": 105,
        "first_name": "Dora",
        "last_name": "Schimoni"
    },
    {
        "id": 106,
        "first_name": "Jerrie",
        "last_name": "Revance"
    },
    {
        "id": 107,
        "first_name": "Carny",
        "last_name": "Domengue"
    },
    {
        "id": 108,
        "first_name": "Leisha",
        "last_name": "Treuge"
    },
    {
        "id": 109,
        "first_name": "Dunstan",
        "last_name": "Hebard"
    },
    {
        "id": 110,
        "first_name": "Torie",
        "last_name": "Heistermann"
    },
    {
        "id": 111,
        "first_name": "Lani",
        "last_name": "Avon"
    },
    {
        "id": 112,
        "first_name": "Ashbey",
        "last_name": "Arthan"
    },
    {
        "id": 113,
        "first_name": "Cynthia",
        "last_name": "Pryde"
    },
    {
        "id": 114,
        "first_name": "Kerry",
        "last_name": "Campanelli"
    },
    {
        "id": 115,
        "first_name": "Shelba",
        "last_name": "Treharne"
    },
    {
        "id": 116,
        "first_name": "Kale",
        "last_name": "Liebmann"
    },
    {
        "id": 117,
        "first_name": "Gran",
        "last_name": "Zanetello"
    },
    {
        "id": 118,
        "first_name": "Ferdinand",
        "last_name": "Press"
    },
    {
        "id": 119,
        "first_name": "Carolus",
        "last_name": "Grayland"
    },
    {
        "id": 120,
        "first_name": "Rowney",
        "last_name": "Gee"
    },
    {
        "id": 121,
        "first_name": "Mackenzie",
        "last_name": "Brackpool"
    },
    {
        "id": 122,
        "first_name": "Regan",
        "last_name": "Geraghty"
    },
    {
        "id": 123,
        "first_name": "Roseann",
        "last_name": "Blackshaw"
    },
    {
        "id": 124,
        "first_name": "Vivianne",
        "last_name": "Iacovini"
    },
    {
        "id": 125,
        "first_name": "Tait",
        "last_name": "Dory"
    },
    {
        "id": 126,
        "first_name": "Ajay",
        "last_name": "Pllu"
    },
    {
        "id": 127,
        "first_name": "Lelia",
        "last_name": "Springer"
    },
    {
        "id": 128,
        "first_name": "Gregorio",
        "last_name": "Attenbrow"
    },
    {
        "id": 129,
        "first_name": "Barbe",
        "last_name": "Phillippo"
    },
    {
        "id": 130,
        "first_name": "Lizbeth",
        "last_name": "Beese"
    },
    {
        "id": 131,
        "first_name": "Tomi",
        "last_name": "Morgue"
    },
    {
        "id": 132,
        "first_name": "Dag",
        "last_name": "Shorter"
    },
    {
        "id": 133,
        "first_name": "Teddie",
        "last_name": "Shakespeare"
    },
    {
        "id": 134,
        "first_name": "Chastity",
        "last_name": "Gyrgorcewicx"
    },
    {
        "id": 135,
        "first_name": "Tatiania",
        "last_name": "Stringman"
    },
    {
        "id": 136,
        "first_name": "Rem",
        "last_name": "Faye"
    },
    {
        "id": 137,
        "first_name": "Duky",
        "last_name": "Martonfi"
    },
    {
        "id": 138,
        "first_name": "Jimmy",
        "last_name": "Kegg"
    },
    {
        "id": 139,
        "first_name": "Hadleigh",
        "last_name": "Kirkman"
    },
    {
        "id": 140,
        "first_name": "Nydia",
        "last_name": "Godspeede"
    },
    {
        "id": 141,
        "first_name": "Cheri",
        "last_name": "Clothier"
    },
    {
        "id": 142,
        "first_name": "Eveline",
        "last_name": "Sarfas"
    },
    {
        "id": 143,
        "first_name": "Germain",
        "last_name": "Weekland"
    },
    {
        "id": 144,
        "first_name": "Jonis",
        "last_name": "Josefsohn"
    },
    {
        "id": 145,
        "first_name": "Meara",
        "last_name": "Noulton"
    },
    {
        "id": 146,
        "first_name": "Page",
        "last_name": "Dixon"
    },
    {
        "id": 147,
        "first_name": "Farrel",
        "last_name": "Seawell"
    },
    {
        "id": 148,
        "first_name": "Sharl",
        "last_name": "Schooley"
    },
    {
        "id": 149,
        "first_name": "Cindee",
        "last_name": "Jeyness"
    },
    {
        "id": 150,
        "first_name": "Denys",
        "last_name": "Casolla"
    },
    {
        "id": 151,
        "first_name": "Erica",
        "last_name": "Petersen"
    },
    {
        "id": 152,
        "first_name": "Devina",
        "last_name": "Deakin"
    },
    {
        "id": 153,
        "first_name": "Bud",
        "last_name": "Bisset"
    },
    {
        "id": 154,
        "first_name": "Orv",
        "last_name": "Kevlin"
    },
    {
        "id": 155,
        "first_name": "Anabelle",
        "last_name": "Sleeny"
    },
    {
        "id": 156,
        "first_name": "Kala",
        "last_name": "Kilsby"
    },
    {
        "id": 157,
        "first_name": "Larry",
        "last_name": "Grimmett"
    },
    {
        "id": 158,
        "first_name": "Nero",
        "last_name": "Parnall"
    },
    {
        "id": 159,
        "first_name": "Rudolf",
        "last_name": "Hemmingway"
    },
    {
        "id": 160,
        "first_name": "Cody",
        "last_name": "Defty"
    },
    {
        "id": 161,
        "first_name": "Dermot",
        "last_name": "McEwan"
    },
    {
        "id": 162,
        "first_name": "Mildrid",
        "last_name": "Blenkin"
    },
    {
        "id": 163,
        "first_name": "Herb",
        "last_name": "Lorrain"
    },
    {
        "id": 164,
        "first_name": "Carissa",
        "last_name": "Anthonsen"
    },
    {
        "id": 165,
        "first_name": "Merle",
        "last_name": "Delooze"
    },
    {
        "id": 166,
        "first_name": "Lizzy",
        "last_name": "Walshe"
    },
    {
        "id": 167,
        "first_name": "Zacharie",
        "last_name": "Heskey"
    },
    {
        "id": 168,
        "first_name": "Sim",
        "last_name": "De Banke"
    },
    {
        "id": 169,
        "first_name": "Mark",
        "last_name": "Jeffryes"
    },
    {
        "id": 170,
        "first_name": "Kevon",
        "last_name": "Ticic"
    },
    {
        "id": 171,
        "first_name": "Barbabas",
        "last_name": "Bakhrushin"
    },
    {
        "id": 172,
        "first_name": "Martainn",
        "last_name": "Cussen"
    },
    {
        "id": 173,
        "first_name": "Verney",
        "last_name": "Cosgrave"
    },
    {
        "id": 174,
        "first_name": "Nero",
        "last_name": "Elijah"
    },
    {
        "id": 175,
        "first_name": "Leonerd",
        "last_name": "Hawler"
    },
    {
        "id": 176,
        "first_name": "Sile",
        "last_name": "Torrent"
    },
    {
        "id": 177,
        "first_name": "Carey",
        "last_name": "McRoberts"
    },
    {
        "id": 178,
        "first_name": "Terrijo",
        "last_name": "Mitchely"
    },
    {
        "id": 179,
        "first_name": "Boot",
        "last_name": "Pemble"
    },
    {
        "id": 180,
        "first_name": "Colline",
        "last_name": "Penhall"
    },
    {
        "id": 181,
        "first_name": "Reggi",
        "last_name": "Stearley"
    },
    {
        "id": 182,
        "first_name": "Jarvis",
        "last_name": "Doulton"
    },
    {
        "id": 183,
        "first_name": "Ibby",
        "last_name": "Le Maitre"
    },
    {
        "id": 184,
        "first_name": "Tudor",
        "last_name": "Foxley"
    },
    {
        "id": 185,
        "first_name": "Zenia",
        "last_name": "Pristnor"
    },
    {
        "id": 186,
        "first_name": "Myles",
        "last_name": "Bithany"
    },
    {
        "id": 187,
        "first_name": "Graham",
        "last_name": "Skegg"
    },
    {
        "id": 188,
        "first_name": "Alejoa",
        "last_name": "Ferrant"
    },
    {
        "id": 189,
        "first_name": "Elie",
        "last_name": "Wasiel"
    },
    {
        "id": 190,
        "first_name": "Fonz",
        "last_name": "Mewhirter"
    },
    {
        "id": 191,
        "first_name": "Heloise",
        "last_name": "Corringham"
    },
    {
        "id": 192,
        "first_name": "Cazzie",
        "last_name": "Fermer"
    },
    {
        "id": 193,
        "first_name": "Tarra",
        "last_name": "Haysman"
    },
    {
        "id": 194,
        "first_name": "Ardene",
        "last_name": "Beyne"
    },
    {
        "id": 195,
        "first_name": "Blinnie",
        "last_name": "Cutchee"
    },
    {
        "id": 196,
        "first_name": "Lothaire",
        "last_name": "Bigglestone"
    },
    {
        "id": 197,
        "first_name": "Clarita",
        "last_name": "Burnsyde"
    },
    {
        "id": 198,
        "first_name": "Ransell",
        "last_name": "Deare"
    },
    {
        "id": 199,
        "first_name": "Kimberly",
        "last_name": "Tansill"
    },
    {
        "id": 200,
        "first_name": "Ursuline",
        "last_name": "Cano"
    },
    {
        "id": 201,
        "first_name": "Russ",
        "last_name": "George"
    },
    {
        "id": 202,
        "first_name": "Ronalda",
        "last_name": "Winsome"
    },
    {
        "id": 203,
        "first_name": "Samuel",
        "last_name": "Greensall"
    },
    {
        "id": 204,
        "first_name": "Rayshell",
        "last_name": "Frisby"
    },
    {
        "id": 205,
        "first_name": "Saunder",
        "last_name": "Duffer"
    },
    {
        "id": 206,
        "first_name": "Inness",
        "last_name": "Climo"
    },
    {
        "id": 207,
        "first_name": "Beilul",
        "last_name": "Calan"
    },
    {
        "id": 208,
        "first_name": "Chancey",
        "last_name": "Narramore"
    },
    {
        "id": 209,
        "first_name": "Cary",
        "last_name": "Millott"
    },
    {
        "id": 210,
        "first_name": "Glennis",
        "last_name": "Pollastro"
    },
    {
        "id": 211,
        "first_name": "Martie",
        "last_name": "Surmeyers"
    },
    {
        "id": 212,
        "first_name": "Lelah",
        "last_name": "Swinford"
    },
    {
        "id": 213,
        "first_name": "Julietta",
        "last_name": "Torrejon"
    },
    {
        "id": 214,
        "first_name": "Lotti",
        "last_name": "Sprull"
    },
    {
        "id": 215,
        "first_name": "Jarid",
        "last_name": "Yitzhakof"
    },
    {
        "id": 216,
        "first_name": "Thorndike",
        "last_name": "Entres"
    },
    {
        "id": 217,
        "first_name": "Merrilee",
        "last_name": "Rottenbury"
    },
    {
        "id": 218,
        "first_name": "Ediva",
        "last_name": "Wardlaw"
    },
    {
        "id": 219,
        "first_name": "Hana",
        "last_name": "Ganiford"
    },
    {
        "id": 220,
        "first_name": "Walliw",
        "last_name": "Bullman"
    },
    {
        "id": 221,
        "first_name": "Clementine",
        "last_name": "Vennart"
    },
    {
        "id": 222,
        "first_name": "Ferne",
        "last_name": "Petronis"
    },
    {
        "id": 223,
        "first_name": "Killie",
        "last_name": "Westmancoat"
    },
    {
        "id": 224,
        "first_name": "Tobi",
        "last_name": "Gouldthorpe"
    },
    {
        "id": 225,
        "first_name": "Krispin",
        "last_name": "Bowdon"
    },
    {
        "id": 226,
        "first_name": "Clare",
        "last_name": "Winstanley"
    },
    {
        "id": 227,
        "first_name": "Lanie",
        "last_name": "Ismead"
    },
    {
        "id": 228,
        "first_name": "Debee",
        "last_name": "Hurlestone"
    },
    {
        "id": 229,
        "first_name": "Yale",
        "last_name": "Harnwell"
    },
    {
        "id": 230,
        "first_name": "Faye",
        "last_name": "Scrancher"
    },
    {
        "id": 231,
        "first_name": "Waylon",
        "last_name": "Pickover"
    },
    {
        "id": 232,
        "first_name": "Bryana",
        "last_name": "Meegin"
    },
    {
        "id": 233,
        "first_name": "Wandis",
        "last_name": "Neeves"
    },
    {
        "id": 234,
        "first_name": "Monte",
        "last_name": "Fieldstone"
    },
    {
        "id": 235,
        "first_name": "Auguste",
        "last_name": "Jentet"
    },
    {
        "id": 236,
        "first_name": "Turner",
        "last_name": "Plumb"
    },
    {
        "id": 237,
        "first_name": "Sigismund",
        "last_name": "Leftley"
    },
    {
        "id": 238,
        "first_name": "Chic",
        "last_name": "Pickle"
    },
    {
        "id": 239,
        "first_name": "Sapphire",
        "last_name": "Dies"
    },
    {
        "id": 240,
        "first_name": "Marice",
        "last_name": "Hannabuss"
    },
    {
        "id": 241,
        "first_name": "Fielding",
        "last_name": "Nuth"
    },
    {
        "id": 242,
        "first_name": "Liva",
        "last_name": "Tourle"
    },
    {
        "id": 243,
        "first_name": "Amandi",
        "last_name": "Howselee"
    },
    {
        "id": 244,
        "first_name": "Ronica",
        "last_name": "Hamlin"
    },
    {
        "id": 245,
        "first_name": "Carolyn",
        "last_name": "Labuschagne"
    },
    {
        "id": 246,
        "first_name": "Berna",
        "last_name": "Considine"
    },
    {
        "id": 247,
        "first_name": "Lizette",
        "last_name": "Mordie"
    },
    {
        "id": 248,
        "first_name": "Hashim",
        "last_name": "Morriss"
    },
    {
        "id": 249,
        "first_name": "Clotilda",
        "last_name": "Spratley"
    },
    {
        "id": 250,
        "first_name": "Jobyna",
        "last_name": "Featherby"
    },
    {
        "id": 251,
        "first_name": "Keri",
        "last_name": "Honniebal"
    },
    {
        "id": 252,
        "first_name": "Phillis",
        "last_name": "Tradewell"
    },
    {
        "id": 253,
        "first_name": "Nicoli",
        "last_name": "Benito"
    },
    {
        "id": 254,
        "first_name": "Birch",
        "last_name": "Laytham"
    },
    {
        "id": 255,
        "first_name": "Jacenta",
        "last_name": "Blondell"
    },
    {
        "id": 256,
        "first_name": "Kendre",
        "last_name": "Fairhall"
    },
    {
        "id": 257,
        "first_name": "Cello",
        "last_name": "Charte"
    },
    {
        "id": 258,
        "first_name": "Pernell",
        "last_name": "Folbige"
    },
    {
        "id": 259,
        "first_name": "Carroll",
        "last_name": "Dakin"
    },
    {
        "id": 260,
        "first_name": "Nelly",
        "last_name": "Varker"
    },
    {
        "id": 261,
        "first_name": "Falito",
        "last_name": "Duerden"
    },
    {
        "id": 262,
        "first_name": "Alaster",
        "last_name": "O'Reagan"
    },
    {
        "id": 263,
        "first_name": "Aubry",
        "last_name": "Soames"
    },
    {
        "id": 264,
        "first_name": "Marve",
        "last_name": "Wardell"
    },
    {
        "id": 265,
        "first_name": "Jacquie",
        "last_name": "Pettifer"
    },
    {
        "id": 266,
        "first_name": "Benedict",
        "last_name": "Guiton"
    },
    {
        "id": 267,
        "first_name": "Ulrike",
        "last_name": "Wash"
    },
    {
        "id": 268,
        "first_name": "Annalee",
        "last_name": "McGannon"
    },
    {
        "id": 269,
        "first_name": "Lia",
        "last_name": "Schulke"
    },
    {
        "id": 270,
        "first_name": "Yul",
        "last_name": "Rizziello"
    },
    {
        "id": 271,
        "first_name": "Brittany",
        "last_name": "Glynne"
    },
    {
        "id": 272,
        "first_name": "Fern",
        "last_name": "Mathieu"
    },
    {
        "id": 273,
        "first_name": "Owen",
        "last_name": "Evennett"
    },
    {
        "id": 274,
        "first_name": "Elyse",
        "last_name": "Titcumb"
    },
    {
        "id": 275,
        "first_name": "Enrico",
        "last_name": "Reddington"
    },
    {
        "id": 276,
        "first_name": "Felecia",
        "last_name": "Phillips"
    },
    {
        "id": 277,
        "first_name": "Lissy",
        "last_name": "Dunbabin"
    },
    {
        "id": 278,
        "first_name": "Dennie",
        "last_name": "Frewer"
    },
    {
        "id": 279,
        "first_name": "Jacob",
        "last_name": "Yegorovnin"
    },
    {
        "id": 280,
        "first_name": "Perry",
        "last_name": "Timms"
    },
    {
        "id": 281,
        "first_name": "Corbin",
        "last_name": "Sheddan"
    },
    {
        "id": 282,
        "first_name": "Hersh",
        "last_name": "Biasotti"
    },
    {
        "id": 283,
        "first_name": "Reidar",
        "last_name": "Carlile"
    },
    {
        "id": 284,
        "first_name": "Mei",
        "last_name": "Sparsholt"
    },
    {
        "id": 285,
        "first_name": "Dermot",
        "last_name": "Echallier"
    },
    {
        "id": 286,
        "first_name": "Alethea",
        "last_name": "Jezard"
    },
    {
        "id": 287,
        "first_name": "Caitrin",
        "last_name": "Barkway"
    },
    {
        "id": 288,
        "first_name": "Sergent",
        "last_name": "Dozdill"
    },
    {
        "id": 289,
        "first_name": "Quinton",
        "last_name": "Somers"
    },
    {
        "id": 290,
        "first_name": "Bobina",
        "last_name": "Vanichkin"
    },
    {
        "id": 291,
        "first_name": "Modestia",
        "last_name": "Crampton"
    },
    {
        "id": 292,
        "first_name": "Evelina",
        "last_name": "Tyreman"
    },
    {
        "id": 293,
        "first_name": "Jeane",
        "last_name": "De Matteis"
    },
    {
        "id": 294,
        "first_name": "Zorana",
        "last_name": "Hiland"
    },
    {
        "id": 295,
        "first_name": "Rose",
        "last_name": "Marcus"
    },
    {
        "id": 296,
        "first_name": "Meta",
        "last_name": "Bree"
    },
    {
        "id": 297,
        "first_name": "Cash",
        "last_name": "Cadreman"
    },
    {
        "id": 298,
        "first_name": "Winfield",
        "last_name": "Greet"
    },
    {
        "id": 299,
        "first_name": "Francklin",
        "last_name": "Shernock"
    },
    {
        "id": 300,
        "first_name": "Madeleine",
        "last_name": "Huckfield"
    },
    {
        "id": 301,
        "first_name": "Loella",
        "last_name": "Willmott"
    },
    {
        "id": 302,
        "first_name": "Heida",
        "last_name": "Huleatt"
    },
    {
        "id": 303,
        "first_name": "Seamus",
        "last_name": "Brookbank"
    },
    {
        "id": 304,
        "first_name": "Livvyy",
        "last_name": "Kenn"
    },
    {
        "id": 305,
        "first_name": "Tremain",
        "last_name": "Yellowlea"
    },
    {
        "id": 306,
        "first_name": "Imogene",
        "last_name": "Drepp"
    },
    {
        "id": 307,
        "first_name": "Sheffield",
        "last_name": "Powdrell"
    },
    {
        "id": 308,
        "first_name": "Humfried",
        "last_name": "Nemchinov"
    },
    {
        "id": 309,
        "first_name": "Jenna",
        "last_name": "Raven"
    },
    {
        "id": 310,
        "first_name": "Sasha",
        "last_name": "Jumont"
    },
    {
        "id": 311,
        "first_name": "Darn",
        "last_name": "Vasyukhnov"
    },
    {
        "id": 312,
        "first_name": "Rania",
        "last_name": "Keyser"
    },
    {
        "id": 313,
        "first_name": "Jaquith",
        "last_name": "Lindner"
    },
    {
        "id": 314,
        "first_name": "Anabelle",
        "last_name": "Wenn"
    },
    {
        "id": 315,
        "first_name": "Katharyn",
        "last_name": "Forgan"
    },
    {
        "id": 316,
        "first_name": "Earl",
        "last_name": "Thickins"
    },
    {
        "id": 317,
        "first_name": "Harmon",
        "last_name": "Bagge"
    },
    {
        "id": 318,
        "first_name": "Riannon",
        "last_name": "Kleiner"
    },
    {
        "id": 319,
        "first_name": "Cammy",
        "last_name": "Gong"
    },
    {
        "id": 320,
        "first_name": "Tisha",
        "last_name": "Lindenblatt"
    },
    {
        "id": 321,
        "first_name": "Martina",
        "last_name": "Seldner"
    },
    {
        "id": 322,
        "first_name": "Aarika",
        "last_name": "Fibbit"
    },
    {
        "id": 323,
        "first_name": "Lizzy",
        "last_name": "Ricardot"
    },
    {
        "id": 324,
        "first_name": "Sharai",
        "last_name": "Canham"
    },
    {
        "id": 325,
        "first_name": "Gus",
        "last_name": "Mangan"
    },
    {
        "id": 326,
        "first_name": "Nariko",
        "last_name": "Hawe"
    },
    {
        "id": 327,
        "first_name": "Judon",
        "last_name": "Bartels"
    },
    {
        "id": 328,
        "first_name": "Elfrieda",
        "last_name": "Bergin"
    },
    {
        "id": 329,
        "first_name": "Emmerich",
        "last_name": "Tesyro"
    },
    {
        "id": 330,
        "first_name": "Inger",
        "last_name": "Chaperling"
    },
    {
        "id": 331,
        "first_name": "Bonnie",
        "last_name": "Storah"
    },
    {
        "id": 332,
        "first_name": "Paulie",
        "last_name": "Darree"
    },
    {
        "id": 333,
        "first_name": "Daile",
        "last_name": "Fildes"
    },
    {
        "id": 334,
        "first_name": "Charley",
        "last_name": "Story"
    },
    {
        "id": 335,
        "first_name": "Toddy",
        "last_name": "Toyne"
    },
    {
        "id": 336,
        "first_name": "Georgy",
        "last_name": "Libermore"
    },
    {
        "id": 337,
        "first_name": "Miguel",
        "last_name": "Evans"
    },
    {
        "id": 338,
        "first_name": "Curran",
        "last_name": "Gartery"
    },
    {
        "id": 339,
        "first_name": "Marylin",
        "last_name": "McVaugh"
    },
    {
        "id": 340,
        "first_name": "Issi",
        "last_name": "Heining"
    },
    {
        "id": 341,
        "first_name": "Sherry",
        "last_name": "Devote"
    },
    {
        "id": 342,
        "first_name": "Eb",
        "last_name": "Overlow"
    },
    {
        "id": 343,
        "first_name": "Euell",
        "last_name": "Haquin"
    },
    {
        "id": 344,
        "first_name": "Anetta",
        "last_name": "Orsay"
    },
    {
        "id": 345,
        "first_name": "Sonni",
        "last_name": "Zuanazzi"
    },
    {
        "id": 346,
        "first_name": "Hillel",
        "last_name": "Kilkenny"
    },
    {
        "id": 347,
        "first_name": "Willow",
        "last_name": "Elcum"
    },
    {
        "id": 348,
        "first_name": "Cristine",
        "last_name": "Waistall"
    },
    {
        "id": 349,
        "first_name": "Rona",
        "last_name": "Cadney"
    },
    {
        "id": 350,
        "first_name": "Debbi",
        "last_name": "McTerrelly"
    },
    {
        "id": 351,
        "first_name": "Avrit",
        "last_name": "Suttaby"
    },
    {
        "id": 352,
        "first_name": "Conn",
        "last_name": "Dodsley"
    },
    {
        "id": 353,
        "first_name": "Jackquelin",
        "last_name": "Keigher"
    },
    {
        "id": 354,
        "first_name": "Welby",
        "last_name": "MacGinney"
    },
    {
        "id": 355,
        "first_name": "Delano",
        "last_name": "McRobbie"
    },
    {
        "id": 356,
        "first_name": "Ilyssa",
        "last_name": "Wiffield"
    },
    {
        "id": 357,
        "first_name": "Gale",
        "last_name": "Stivens"
    },
    {
        "id": 358,
        "first_name": "Timothee",
        "last_name": "Peele"
    },
    {
        "id": 359,
        "first_name": "Arleen",
        "last_name": "Ellerman"
    },
    {
        "id": 360,
        "first_name": "Artur",
        "last_name": "Twittey"
    },
    {
        "id": 361,
        "first_name": "Lucretia",
        "last_name": "McCoughan"
    },
    {
        "id": 362,
        "first_name": "Gwenny",
        "last_name": "Haggerstone"
    },
    {
        "id": 363,
        "first_name": "Darline",
        "last_name": "Dobey"
    },
    {
        "id": 364,
        "first_name": "Debee",
        "last_name": "Roisen"
    },
    {
        "id": 365,
        "first_name": "Britni",
        "last_name": "Goatcher"
    },
    {
        "id": 366,
        "first_name": "Elton",
        "last_name": "Bicker"
    },
    {
        "id": 367,
        "first_name": "Jaquelyn",
        "last_name": "Siaskowski"
    },
    {
        "id": 368,
        "first_name": "Geoff",
        "last_name": "Baddoe"
    },
    {
        "id": 369,
        "first_name": "Melvyn",
        "last_name": "Morby"
    },
    {
        "id": 370,
        "first_name": "Dougie",
        "last_name": "Cawood"
    },
    {
        "id": 371,
        "first_name": "Sergeant",
        "last_name": "O'Rudden"
    },
    {
        "id": 372,
        "first_name": "Wilek",
        "last_name": "Izakof"
    },
    {
        "id": 373,
        "first_name": "Alberta",
        "last_name": "Carmichael"
    },
    {
        "id": 374,
        "first_name": "Redd",
        "last_name": "Sprake"
    },
    {
        "id": 375,
        "first_name": "Neal",
        "last_name": "Granger"
    },
    {
        "id": 376,
        "first_name": "Damon",
        "last_name": "Learmount"
    },
    {
        "id": 377,
        "first_name": "Merrie",
        "last_name": "McGuffie"
    },
    {
        "id": 378,
        "first_name": "Murray",
        "last_name": "Stuffins"
    },
    {
        "id": 379,
        "first_name": "Staci",
        "last_name": "Di Gregorio"
    },
    {
        "id": 380,
        "first_name": "Rene",
        "last_name": "Heinsh"
    },
    {
        "id": 381,
        "first_name": "Roddy",
        "last_name": "Hantusch"
    },
    {
        "id": 382,
        "first_name": "Rod",
        "last_name": "McNab"
    },
    {
        "id": 383,
        "first_name": "Jerald",
        "last_name": "Gillam"
    },
    {
        "id": 384,
        "first_name": "Archer",
        "last_name": "Keyho"
    },
    {
        "id": 385,
        "first_name": "Roddy",
        "last_name": "Emer"
    },
    {
        "id": 386,
        "first_name": "Earlie",
        "last_name": "Tuppeny"
    },
    {
        "id": 387,
        "first_name": "Nollie",
        "last_name": "Simkin"
    },
    {
        "id": 388,
        "first_name": "Catherin",
        "last_name": "Scoullar"
    },
    {
        "id": 389,
        "first_name": "Jemie",
        "last_name": "Staig"
    },
    {
        "id": 390,
        "first_name": "Brandi",
        "last_name": "Mucklestone"
    },
    {
        "id": 391,
        "first_name": "Tilly",
        "last_name": "Pennetti"
    },
    {
        "id": 392,
        "first_name": "Tynan",
        "last_name": "Skeermer"
    },
    {
        "id": 393,
        "first_name": "Rad",
        "last_name": "Fowlestone"
    },
    {
        "id": 394,
        "first_name": "Rhetta",
        "last_name": "Beggi"
    },
    {
        "id": 395,
        "first_name": "Enrika",
        "last_name": "Salsbury"
    },
    {
        "id": 396,
        "first_name": "Chico",
        "last_name": "Stirling"
    },
    {
        "id": 397,
        "first_name": "Annabel",
        "last_name": "Aberdeen"
    },
    {
        "id": 398,
        "first_name": "Raimundo",
        "last_name": "Spowage"
    },
    {
        "id": 399,
        "first_name": "Shep",
        "last_name": "Timmons"
    },
    {
        "id": 400,
        "first_name": "Cherilyn",
        "last_name": "Derricoat"
    },
    {
        "id": 401,
        "first_name": "Sonny",
        "last_name": "Cassius"
    },
    {
        "id": 402,
        "first_name": "Olva",
        "last_name": "Pactat"
    },
    {
        "id": 403,
        "first_name": "Pippo",
        "last_name": "Ferrandez"
    },
    {
        "id": 404,
        "first_name": "Ravi",
        "last_name": "Delnevo"
    },
    {
        "id": 405,
        "first_name": "Fania",
        "last_name": "Spurway"
    },
    {
        "id": 406,
        "first_name": "Dasi",
        "last_name": "Van Salzberger"
    },
    {
        "id": 407,
        "first_name": "Lester",
        "last_name": "Gammett"
    },
    {
        "id": 408,
        "first_name": "Sheeree",
        "last_name": "Cayley"
    },
    {
        "id": 409,
        "first_name": "Gris",
        "last_name": "Cristoforo"
    },
    {
        "id": 410,
        "first_name": "Dacie",
        "last_name": "Warden"
    },
    {
        "id": 411,
        "first_name": "Maynard",
        "last_name": "Pimmocke"
    },
    {
        "id": 412,
        "first_name": "Elwyn",
        "last_name": "Paynes"
    },
    {
        "id": 413,
        "first_name": "Rinaldo",
        "last_name": "Sagg"
    },
    {
        "id": 414,
        "first_name": "Carey",
        "last_name": "Ridgedell"
    },
    {
        "id": 415,
        "first_name": "Gilligan",
        "last_name": "Mathiasen"
    },
    {
        "id": 416,
        "first_name": "Bethanne",
        "last_name": "Dicky"
    },
    {
        "id": 417,
        "first_name": "Ellerey",
        "last_name": "Copnar"
    },
    {
        "id": 418,
        "first_name": "Arvy",
        "last_name": "Maginot"
    },
    {
        "id": 419,
        "first_name": "Tandie",
        "last_name": "Torfin"
    },
    {
        "id": 420,
        "first_name": "Nickey",
        "last_name": "Hadlow"
    },
    {
        "id": 421,
        "first_name": "Paton",
        "last_name": "Poolton"
    },
    {
        "id": 422,
        "first_name": "Paco",
        "last_name": "Whiten"
    },
    {
        "id": 423,
        "first_name": "Sharity",
        "last_name": "Harcase"
    },
    {
        "id": 424,
        "first_name": "Birdie",
        "last_name": "Mattecot"
    },
    {
        "id": 425,
        "first_name": "Bethina",
        "last_name": "Dory"
    },
    {
        "id": 426,
        "first_name": "Lory",
        "last_name": "Menere"
    },
    {
        "id": 427,
        "first_name": "Joey",
        "last_name": "Brunicke"
    },
    {
        "id": 428,
        "first_name": "Gretal",
        "last_name": "Flippen"
    },
    {
        "id": 429,
        "first_name": "Giordano",
        "last_name": "Giggie"
    },
    {
        "id": 430,
        "first_name": "Lise",
        "last_name": "Neilands"
    },
    {
        "id": 431,
        "first_name": "Markus",
        "last_name": "Minci"
    },
    {
        "id": 432,
        "first_name": "Ervin",
        "last_name": "Halvosen"
    },
    {
        "id": 433,
        "first_name": "Walther",
        "last_name": "Sims"
    },
    {
        "id": 434,
        "first_name": "Margret",
        "last_name": "Crack"
    },
    {
        "id": 435,
        "first_name": "Alie",
        "last_name": "Philpots"
    },
    {
        "id": 436,
        "first_name": "Bibbie",
        "last_name": "McCutheon"
    },
    {
        "id": 437,
        "first_name": "Angelica",
        "last_name": "Gorick"
    },
    {
        "id": 438,
        "first_name": "Shaughn",
        "last_name": "Guerra"
    },
    {
        "id": 439,
        "first_name": "Michelina",
        "last_name": "Ouchterlony"
    },
    {
        "id": 440,
        "first_name": "Giovanna",
        "last_name": "Swateridge"
    },
    {
        "id": 441,
        "first_name": "Sebastien",
        "last_name": "Van der Hoven"
    },
    {
        "id": 442,
        "first_name": "Ingemar",
        "last_name": "Challicum"
    },
    {
        "id": 443,
        "first_name": "Bonny",
        "last_name": "Southan"
    },
    {
        "id": 444,
        "first_name": "Jasmina",
        "last_name": "Aggott"
    },
    {
        "id": 445,
        "first_name": "Fayth",
        "last_name": "Lewsley"
    },
    {
        "id": 446,
        "first_name": "Mamie",
        "last_name": "Thompson"
    },
    {
        "id": 447,
        "first_name": "Liesa",
        "last_name": "Aslam"
    },
    {
        "id": 448,
        "first_name": "Emmye",
        "last_name": "Gebbe"
    },
    {
        "id": 449,
        "first_name": "Eryn",
        "last_name": "McReedy"
    },
    {
        "id": 450,
        "first_name": "Jammal",
        "last_name": "Edgler"
    },
    {
        "id": 451,
        "first_name": "Lauryn",
        "last_name": "Tetsall"
    },
    {
        "id": 452,
        "first_name": "Hanan",
        "last_name": "Posner"
    },
    {
        "id": 453,
        "first_name": "Monte",
        "last_name": "Baldick"
    },
    {
        "id": 454,
        "first_name": "Berry",
        "last_name": "Saunter"
    },
    {
        "id": 455,
        "first_name": "Amandi",
        "last_name": "Lorenzin"
    },
    {
        "id": 456,
        "first_name": "Randie",
        "last_name": "Joblin"
    },
    {
        "id": 457,
        "first_name": "Anjela",
        "last_name": "Kleint"
    },
    {
        "id": 458,
        "first_name": "Kandy",
        "last_name": "Habeshaw"
    },
    {
        "id": 459,
        "first_name": "Thaddus",
        "last_name": "Elphinstone"
    },
    {
        "id": 460,
        "first_name": "Yule",
        "last_name": "Marcos"
    },
    {
        "id": 461,
        "first_name": "Harriott",
        "last_name": "Willsmore"
    },
    {
        "id": 462,
        "first_name": "Louis",
        "last_name": "Strase"
    },
    {
        "id": 463,
        "first_name": "Maurizio",
        "last_name": "Pinching"
    },
    {
        "id": 464,
        "first_name": "Jozef",
        "last_name": "Pooly"
    },
    {
        "id": 465,
        "first_name": "Garland",
        "last_name": "Tejada"
    },
    {
        "id": 466,
        "first_name": "Beale",
        "last_name": "Gillyett"
    },
    {
        "id": 467,
        "first_name": "Tobit",
        "last_name": "Middlehurst"
    },
    {
        "id": 468,
        "first_name": "Haily",
        "last_name": "Sandars"
    },
    {
        "id": 469,
        "first_name": "Angil",
        "last_name": "Durrans"
    },
    {
        "id": 470,
        "first_name": "Blondelle",
        "last_name": "Mattschas"
    },
    {
        "id": 471,
        "first_name": "Zita",
        "last_name": "Crace"
    },
    {
        "id": 472,
        "first_name": "Florri",
        "last_name": "Mccaull"
    },
    {
        "id": 473,
        "first_name": "Dulcy",
        "last_name": "Hector"
    },
    {
        "id": 474,
        "first_name": "Brig",
        "last_name": "Sijmons"
    },
    {
        "id": 475,
        "first_name": "Christina",
        "last_name": "Ducker"
    },
    {
        "id": 476,
        "first_name": "Brnaby",
        "last_name": "Fobidge"
    },
    {
        "id": 477,
        "first_name": "Grant",
        "last_name": "Royal"
    },
    {
        "id": 478,
        "first_name": "Margret",
        "last_name": "Wapplington"
    },
    {
        "id": 479,
        "first_name": "Aubrey",
        "last_name": "Lancaster"
    },
    {
        "id": 480,
        "first_name": "Saxon",
        "last_name": "Beauchamp"
    },
    {
        "id": 481,
        "first_name": "Collete",
        "last_name": "Claybourne"
    },
    {
        "id": 482,
        "first_name": "Gris",
        "last_name": "Balderstone"
    },
    {
        "id": 483,
        "first_name": "Amelie",
        "last_name": "Trembley"
    },
    {
        "id": 484,
        "first_name": "Allissa",
        "last_name": "Asipenko"
    },
    {
        "id": 485,
        "first_name": "Jo-ann",
        "last_name": "Drepp"
    },
    {
        "id": 486,
        "first_name": "Darcy",
        "last_name": "Please"
    },
    {
        "id": 487,
        "first_name": "Madlin",
        "last_name": "Durtnal"
    },
    {
        "id": 488,
        "first_name": "Brew",
        "last_name": "Bailess"
    },
    {
        "id": 489,
        "first_name": "Reinhard",
        "last_name": "Joiris"
    },
    {
        "id": 490,
        "first_name": "Viki",
        "last_name": "Wisbey"
    },
    {
        "id": 491,
        "first_name": "Erica",
        "last_name": "Swain"
    },
    {
        "id": 492,
        "first_name": "Morris",
        "last_name": "Guidone"
    },
    {
        "id": 493,
        "first_name": "Martie",
        "last_name": "Downton"
    },
    {
        "id": 494,
        "first_name": "Zenia",
        "last_name": "Farryann"
    },
    {
        "id": 495,
        "first_name": "Chandler",
        "last_name": "McCarty"
    },
    {
        "id": 496,
        "first_name": "Danny",
        "last_name": "Cosgreave"
    },
    {
        "id": 497,
        "first_name": "Daveta",
        "last_name": "Trawin"
    },
    {
        "id": 498,
        "first_name": "Ignatius",
        "last_name": "Hansley"
    },
    {
        "id": 499,
        "first_name": "Huntington",
        "last_name": "Rothman"
    },
    {
        "id": 500,
        "first_name": "Nara",
        "last_name": "Currom"
    },
    {
        "id": 501,
        "first_name": "Clementius",
        "last_name": "Pendry"
    },
    {
        "id": 502,
        "first_name": "Barbie",
        "last_name": "Faichnie"
    },
    {
        "id": 503,
        "first_name": "Olia",
        "last_name": "Thornton"
    },
    {
        "id": 504,
        "first_name": "Cornela",
        "last_name": "Dunbobin"
    },
    {
        "id": 505,
        "first_name": "Bartolemo",
        "last_name": "Medler"
    },
    {
        "id": 506,
        "first_name": "Natty",
        "last_name": "Tolemache"
    },
    {
        "id": 507,
        "first_name": "Dasi",
        "last_name": "Rosbrough"
    },
    {
        "id": 508,
        "first_name": "Cissiee",
        "last_name": "Varren"
    },
    {
        "id": 509,
        "first_name": "Pierrette",
        "last_name": "Verson"
    },
    {
        "id": 510,
        "first_name": "Gillie",
        "last_name": "Keneleyside"
    },
    {
        "id": 511,
        "first_name": "Putnam",
        "last_name": "Cobbold"
    },
    {
        "id": 512,
        "first_name": "Tedi",
        "last_name": "Jermy"
    },
    {
        "id": 513,
        "first_name": "Ernst",
        "last_name": "Varcoe"
    },
    {
        "id": 514,
        "first_name": "Zed",
        "last_name": "Stening"
    },
    {
        "id": 515,
        "first_name": "Emera",
        "last_name": "Shaudfurth"
    },
    {
        "id": 516,
        "first_name": "Kerry",
        "last_name": "Sappy"
    },
    {
        "id": 517,
        "first_name": "Kimball",
        "last_name": "Murdoch"
    },
    {
        "id": 518,
        "first_name": "Thorny",
        "last_name": "Redding"
    },
    {
        "id": 519,
        "first_name": "Natalina",
        "last_name": "Northwood"
    },
    {
        "id": 520,
        "first_name": "Alyosha",
        "last_name": "Snartt"
    },
    {
        "id": 521,
        "first_name": "Hastings",
        "last_name": "Podmore"
    },
    {
        "id": 522,
        "first_name": "Devin",
        "last_name": "Daine"
    },
    {
        "id": 523,
        "first_name": "Ike",
        "last_name": "McAvaddy"
    },
    {
        "id": 524,
        "first_name": "Avram",
        "last_name": "Clifft"
    },
    {
        "id": 525,
        "first_name": "Cordi",
        "last_name": "McLachlan"
    },
    {
        "id": 526,
        "first_name": "Yoko",
        "last_name": "Hingeley"
    },
    {
        "id": 527,
        "first_name": "Jeane",
        "last_name": "Kochl"
    },
    {
        "id": 528,
        "first_name": "Leonardo",
        "last_name": "Cleef"
    },
    {
        "id": 529,
        "first_name": "Gussi",
        "last_name": "Leak"
    },
    {
        "id": 530,
        "first_name": "Fair",
        "last_name": "Goard"
    },
    {
        "id": 531,
        "first_name": "Maire",
        "last_name": "Ebbage"
    },
    {
        "id": 532,
        "first_name": "Kerk",
        "last_name": "Varnham"
    },
    {
        "id": 533,
        "first_name": "Massimo",
        "last_name": "Butfield"
    },
    {
        "id": 534,
        "first_name": "Collie",
        "last_name": "Brack"
    },
    {
        "id": 535,
        "first_name": "Lionel",
        "last_name": "Horsley"
    },
    {
        "id": 536,
        "first_name": "Abbe",
        "last_name": "Wandrich"
    },
    {
        "id": 537,
        "first_name": "Phelia",
        "last_name": "Evetts"
    },
    {
        "id": 538,
        "first_name": "Lawry",
        "last_name": "Hurndall"
    },
    {
        "id": 539,
        "first_name": "Fitzgerald",
        "last_name": "Sheldrick"
    },
    {
        "id": 540,
        "first_name": "Fidela",
        "last_name": "Shalders"
    },
    {
        "id": 541,
        "first_name": "Curtis",
        "last_name": "Cranshaw"
    },
    {
        "id": 542,
        "first_name": "Merrily",
        "last_name": "Abrahm"
    },
    {
        "id": 543,
        "first_name": "Heinrik",
        "last_name": "Vettore"
    },
    {
        "id": 544,
        "first_name": "Ellen",
        "last_name": "Soughton"
    },
    {
        "id": 545,
        "first_name": "Walther",
        "last_name": "Rizzelli"
    },
    {
        "id": 546,
        "first_name": "Kori",
        "last_name": "Orwell"
    },
    {
        "id": 547,
        "first_name": "Debbi",
        "last_name": "Fishbourn"
    },
    {
        "id": 548,
        "first_name": "Vinny",
        "last_name": "Finan"
    },
    {
        "id": 549,
        "first_name": "Averyl",
        "last_name": "Blurton"
    },
    {
        "id": 550,
        "first_name": "Barry",
        "last_name": "Scalera"
    },
    {
        "id": 551,
        "first_name": "Agnese",
        "last_name": "Rooney"
    },
    {
        "id": 552,
        "first_name": "Merrie",
        "last_name": "Keighley"
    },
    {
        "id": 553,
        "first_name": "Shayna",
        "last_name": "Forsdicke"
    },
    {
        "id": 554,
        "first_name": "Deedee",
        "last_name": "Livzey"
    },
    {
        "id": 555,
        "first_name": "Ham",
        "last_name": "Tzuker"
    },
    {
        "id": 556,
        "first_name": "Bordy",
        "last_name": "Dollard"
    },
    {
        "id": 557,
        "first_name": "Neel",
        "last_name": "Dulanty"
    },
    {
        "id": 558,
        "first_name": "Davide",
        "last_name": "Goundrill"
    },
    {
        "id": 559,
        "first_name": "Erick",
        "last_name": "Pala"
    },
    {
        "id": 560,
        "first_name": "Nevil",
        "last_name": "Swettenham"
    },
    {
        "id": 561,
        "first_name": "Jolee",
        "last_name": "Pigden"
    },
    {
        "id": 562,
        "first_name": "Karney",
        "last_name": "Annes"
    },
    {
        "id": 563,
        "first_name": "Norby",
        "last_name": "Fairbrace"
    },
    {
        "id": 564,
        "first_name": "Lindy",
        "last_name": "McKomb"
    },
    {
        "id": 565,
        "first_name": "Carie",
        "last_name": "Simnel"
    },
    {
        "id": 566,
        "first_name": "Brett",
        "last_name": "Wimmer"
    },
    {
        "id": 567,
        "first_name": "Harper",
        "last_name": "Nevill"
    },
    {
        "id": 568,
        "first_name": "Mickie",
        "last_name": "Jobin"
    },
    {
        "id": 569,
        "first_name": "Bidget",
        "last_name": "Mulvey"
    },
    {
        "id": 570,
        "first_name": "Antone",
        "last_name": "Walding"
    },
    {
        "id": 571,
        "first_name": "Devi",
        "last_name": "Clash"
    },
    {
        "id": 572,
        "first_name": "Neala",
        "last_name": "Shale"
    },
    {
        "id": 573,
        "first_name": "Meade",
        "last_name": "Stoven"
    },
    {
        "id": 574,
        "first_name": "Gretel",
        "last_name": "Scrivner"
    },
    {
        "id": 575,
        "first_name": "Colly",
        "last_name": "Wyld"
    },
    {
        "id": 576,
        "first_name": "Lorri",
        "last_name": "Reeken"
    },
    {
        "id": 577,
        "first_name": "Arlena",
        "last_name": "Esplin"
    },
    {
        "id": 578,
        "first_name": "Minette",
        "last_name": "Bellwood"
    },
    {
        "id": 579,
        "first_name": "Megen",
        "last_name": "Credland"
    },
    {
        "id": 580,
        "first_name": "Riannon",
        "last_name": "Greenough"
    },
    {
        "id": 581,
        "first_name": "Winifred",
        "last_name": "McDuff"
    },
    {
        "id": 582,
        "first_name": "Sorcha",
        "last_name": "Stobbe"
    },
    {
        "id": 583,
        "first_name": "Ursala",
        "last_name": "Puvia"
    },
    {
        "id": 584,
        "first_name": "Locke",
        "last_name": "Confait"
    },
    {
        "id": 585,
        "first_name": "Bengt",
        "last_name": "Quirke"
    },
    {
        "id": 586,
        "first_name": "Brittney",
        "last_name": "Henriques"
    },
    {
        "id": 587,
        "first_name": "Mommy",
        "last_name": "Pindar"
    },
    {
        "id": 588,
        "first_name": "Keenan",
        "last_name": "Hadgraft"
    },
    {
        "id": 589,
        "first_name": "Fran",
        "last_name": "Licciardello"
    },
    {
        "id": 590,
        "first_name": "Padget",
        "last_name": "MacBrearty"
    },
    {
        "id": 591,
        "first_name": "Lillis",
        "last_name": "Moloney"
    },
    {
        "id": 592,
        "first_name": "Jaymee",
        "last_name": "O'Sheeryne"
    },
    {
        "id": 593,
        "first_name": "Antonietta",
        "last_name": "Melladew"
    },
    {
        "id": 594,
        "first_name": "Chas",
        "last_name": "Callum"
    },
    {
        "id": 595,
        "first_name": "Minetta",
        "last_name": "Dellenbach"
    },
    {
        "id": 596,
        "first_name": "Ermentrude",
        "last_name": "Gilcriest"
    },
    {
        "id": 597,
        "first_name": "Cad",
        "last_name": "Pitchers"
    },
    {
        "id": 598,
        "first_name": "Aimee",
        "last_name": "Chaplyn"
    },
    {
        "id": 599,
        "first_name": "Pearline",
        "last_name": "Iannello"
    },
    {
        "id": 600,
        "first_name": "Leighton",
        "last_name": "Spriggs"
    },
    {
        "id": 601,
        "first_name": "Marlin",
        "last_name": "Kuschke"
    },
    {
        "id": 602,
        "first_name": "Prinz",
        "last_name": "Jaskowicz"
    },
    {
        "id": 603,
        "first_name": "Borg",
        "last_name": "Jarrold"
    },
    {
        "id": 604,
        "first_name": "Nan",
        "last_name": "Fawdrey"
    },
    {
        "id": 605,
        "first_name": "Pen",
        "last_name": "Jandourek"
    },
    {
        "id": 606,
        "first_name": "Crawford",
        "last_name": "Yurukhin"
    },
    {
        "id": 607,
        "first_name": "Hope",
        "last_name": "Moy"
    },
    {
        "id": 608,
        "first_name": "Nikolaos",
        "last_name": "Rodger"
    },
    {
        "id": 609,
        "first_name": "Kacey",
        "last_name": "Maruska"
    },
    {
        "id": 610,
        "first_name": "Frazer",
        "last_name": "Spittall"
    },
    {
        "id": 611,
        "first_name": "Hilda",
        "last_name": "Hartop"
    },
    {
        "id": 612,
        "first_name": "Ileane",
        "last_name": "Tandey"
    },
    {
        "id": 613,
        "first_name": "Osmond",
        "last_name": "Matevosian"
    },
    {
        "id": 614,
        "first_name": "Hewe",
        "last_name": "Slayton"
    },
    {
        "id": 615,
        "first_name": "Sisile",
        "last_name": "Waadenburg"
    },
    {
        "id": 616,
        "first_name": "Ulrika",
        "last_name": "Skill"
    },
    {
        "id": 617,
        "first_name": "Darby",
        "last_name": "Casero"
    },
    {
        "id": 618,
        "first_name": "Garvin",
        "last_name": "Petran"
    },
    {
        "id": 619,
        "first_name": "Nicky",
        "last_name": "Schubart"
    },
    {
        "id": 620,
        "first_name": "Sue",
        "last_name": "Kirton"
    },
    {
        "id": 621,
        "first_name": "Alleen",
        "last_name": "Farres"
    },
    {
        "id": 622,
        "first_name": "Shanta",
        "last_name": "Brydone"
    },
    {
        "id": 623,
        "first_name": "Rosalie",
        "last_name": "Rickert"
    },
    {
        "id": 624,
        "first_name": "Pamela",
        "last_name": "Bacup"
    },
    {
        "id": 625,
        "first_name": "Lemmy",
        "last_name": "Flacknoe"
    },
    {
        "id": 626,
        "first_name": "Wallie",
        "last_name": "Tames"
    },
    {
        "id": 627,
        "first_name": "Rubi",
        "last_name": "Boughen"
    },
    {
        "id": 628,
        "first_name": "Marcelline",
        "last_name": "Jeandon"
    },
    {
        "id": 629,
        "first_name": "Veronika",
        "last_name": "Licas"
    },
    {
        "id": 630,
        "first_name": "Gwynne",
        "last_name": "Spurnier"
    },
    {
        "id": 631,
        "first_name": "Raoul",
        "last_name": "Danieli"
    },
    {
        "id": 632,
        "first_name": "Stearn",
        "last_name": "Truder"
    },
    {
        "id": 633,
        "first_name": "Chevy",
        "last_name": "Worvill"
    },
    {
        "id": 634,
        "first_name": "Dud",
        "last_name": "Cokely"
    },
    {
        "id": 635,
        "first_name": "Cami",
        "last_name": "Botly"
    },
    {
        "id": 636,
        "first_name": "Rickard",
        "last_name": "Gundrey"
    },
    {
        "id": 637,
        "first_name": "Arney",
        "last_name": "Ivashinnikov"
    },
    {
        "id": 638,
        "first_name": "Neilla",
        "last_name": "Credland"
    },
    {
        "id": 639,
        "first_name": "Janene",
        "last_name": "Hodinton"
    },
    {
        "id": 640,
        "first_name": "Lucias",
        "last_name": "MacGillreich"
    },
    {
        "id": 641,
        "first_name": "Bliss",
        "last_name": "Bediss"
    },
    {
        "id": 642,
        "first_name": "Deny",
        "last_name": "Renihan"
    },
    {
        "id": 643,
        "first_name": "Farrel",
        "last_name": "Llewellen"
    },
    {
        "id": 644,
        "first_name": "Sybille",
        "last_name": "Antos"
    },
    {
        "id": 645,
        "first_name": "Anson",
        "last_name": "Murcott"
    },
    {
        "id": 646,
        "first_name": "Ardine",
        "last_name": "Duddridge"
    },
    {
        "id": 647,
        "first_name": "Tootsie",
        "last_name": "Figin"
    },
    {
        "id": 648,
        "first_name": "Carma",
        "last_name": "Sandry"
    },
    {
        "id": 649,
        "first_name": "Farrel",
        "last_name": "Devonshire"
    },
    {
        "id": 650,
        "first_name": "Travus",
        "last_name": "Bouller"
    },
    {
        "id": 651,
        "first_name": "Stefania",
        "last_name": "Plews"
    },
    {
        "id": 652,
        "first_name": "Auroora",
        "last_name": "Pluvier"
    },
    {
        "id": 653,
        "first_name": "Natassia",
        "last_name": "Hammersley"
    },
    {
        "id": 654,
        "first_name": "Barret",
        "last_name": "Gillebert"
    },
    {
        "id": 655,
        "first_name": "Chance",
        "last_name": "Alger"
    },
    {
        "id": 656,
        "first_name": "Zollie",
        "last_name": "Thebeaud"
    },
    {
        "id": 657,
        "first_name": "Karylin",
        "last_name": "Garmon"
    },
    {
        "id": 658,
        "first_name": "Morgen",
        "last_name": "Lewsy"
    },
    {
        "id": 659,
        "first_name": "Orran",
        "last_name": "Frankis"
    },
    {
        "id": 660,
        "first_name": "Carlee",
        "last_name": "Bake"
    },
    {
        "id": 661,
        "first_name": "Hillel",
        "last_name": "Lomasney"
    },
    {
        "id": 662,
        "first_name": "Lemar",
        "last_name": "Petzold"
    },
    {
        "id": 663,
        "first_name": "Carleen",
        "last_name": "Clibbery"
    },
    {
        "id": 664,
        "first_name": "Leanna",
        "last_name": "Venard"
    },
    {
        "id": 665,
        "first_name": "Elwira",
        "last_name": "Durrans"
    },
    {
        "id": 666,
        "first_name": "Olia",
        "last_name": "Paradin"
    },
    {
        "id": 667,
        "first_name": "Filmer",
        "last_name": "Adds"
    },
    {
        "id": 668,
        "first_name": "Carlina",
        "last_name": "Whitemarsh"
    },
    {
        "id": 669,
        "first_name": "Nanice",
        "last_name": "Feldberg"
    },
    {
        "id": 670,
        "first_name": "Jerrilee",
        "last_name": "Lafaye"
    },
    {
        "id": 671,
        "first_name": "Alfredo",
        "last_name": "Rushbrook"
    },
    {
        "id": 672,
        "first_name": "Darline",
        "last_name": "Mascall"
    },
    {
        "id": 673,
        "first_name": "Orelie",
        "last_name": "Goodridge"
    },
    {
        "id": 674,
        "first_name": "Agnes",
        "last_name": "Gutsell"
    },
    {
        "id": 675,
        "first_name": "Sidonnie",
        "last_name": "Hector"
    },
    {
        "id": 676,
        "first_name": "Luca",
        "last_name": "Vaun"
    },
    {
        "id": 677,
        "first_name": "Ban",
        "last_name": "Tibbetts"
    },
    {
        "id": 678,
        "first_name": "Cart",
        "last_name": "Bryers"
    },
    {
        "id": 679,
        "first_name": "Korie",
        "last_name": "Dugmore"
    },
    {
        "id": 680,
        "first_name": "Meggi",
        "last_name": "Arson"
    },
    {
        "id": 681,
        "first_name": "Ninnette",
        "last_name": "L'Episcopi"
    },
    {
        "id": 682,
        "first_name": "Benoite",
        "last_name": "Lettley"
    },
    {
        "id": 683,
        "first_name": "Bobby",
        "last_name": "Leidecker"
    },
    {
        "id": 684,
        "first_name": "Cris",
        "last_name": "Matterdace"
    },
    {
        "id": 685,
        "first_name": "Anya",
        "last_name": "MacNamee"
    },
    {
        "id": 686,
        "first_name": "Jenine",
        "last_name": "Seegar"
    },
    {
        "id": 687,
        "first_name": "Maurice",
        "last_name": "Oswald"
    },
    {
        "id": 688,
        "first_name": "Rici",
        "last_name": "Esser"
    },
    {
        "id": 689,
        "first_name": "Madelina",
        "last_name": "Hully"
    },
    {
        "id": 690,
        "first_name": "Demetris",
        "last_name": "Majury"
    },
    {
        "id": 691,
        "first_name": "Modestia",
        "last_name": "Danilchev"
    },
    {
        "id": 692,
        "first_name": "Jasun",
        "last_name": "Gommery"
    },
    {
        "id": 693,
        "first_name": "Burnaby",
        "last_name": "Mapledoram"
    },
    {
        "id": 694,
        "first_name": "Ethelind",
        "last_name": "Silverton"
    },
    {
        "id": 695,
        "first_name": "Brandea",
        "last_name": "Vickar"
    },
    {
        "id": 696,
        "first_name": "Dermot",
        "last_name": "Sayward"
    },
    {
        "id": 697,
        "first_name": "Layton",
        "last_name": "Haskayne"
    },
    {
        "id": 698,
        "first_name": "Corette",
        "last_name": "Hulson"
    },
    {
        "id": 699,
        "first_name": "Bernie",
        "last_name": "Cohn"
    },
    {
        "id": 700,
        "first_name": "Darbee",
        "last_name": "Brimman"
    },
    {
        "id": 701,
        "first_name": "Lilllie",
        "last_name": "Colum"
    },
    {
        "id": 702,
        "first_name": "Crawford",
        "last_name": "Wildber"
    },
    {
        "id": 703,
        "first_name": "Ches",
        "last_name": "Spratt"
    },
    {
        "id": 704,
        "first_name": "Lem",
        "last_name": "Birth"
    },
    {
        "id": 705,
        "first_name": "Alvera",
        "last_name": "Krzyzowski"
    },
    {
        "id": 706,
        "first_name": "Lena",
        "last_name": "McCrossan"
    },
    {
        "id": 707,
        "first_name": "Sauncho",
        "last_name": "Raynard"
    },
    {
        "id": 708,
        "first_name": "Gale",
        "last_name": "MacCole"
    },
    {
        "id": 709,
        "first_name": "Land",
        "last_name": "McAdam"
    },
    {
        "id": 710,
        "first_name": "Gerta",
        "last_name": "Winchcombe"
    },
    {
        "id": 711,
        "first_name": "Caroljean",
        "last_name": "Cordes"
    },
    {
        "id": 712,
        "first_name": "Dunstan",
        "last_name": "Witch"
    },
    {
        "id": 713,
        "first_name": "William",
        "last_name": "Clark"
    },
    {
        "id": 714,
        "first_name": "Dena",
        "last_name": "Barley"
    },
    {
        "id": 715,
        "first_name": "Dorey",
        "last_name": "Byrde"
    },
    {
        "id": 716,
        "first_name": "Juan",
        "last_name": "McClarence"
    },
    {
        "id": 717,
        "first_name": "Elladine",
        "last_name": "Janson"
    },
    {
        "id": 718,
        "first_name": "Jeremie",
        "last_name": "Griffithe"
    },
    {
        "id": 719,
        "first_name": "Palm",
        "last_name": "Valenta"
    },
    {
        "id": 720,
        "first_name": "Shelli",
        "last_name": "Biggadyke"
    },
    {
        "id": 721,
        "first_name": "Eimile",
        "last_name": "Brunelleschi"
    },
    {
        "id": 722,
        "first_name": "Dallis",
        "last_name": "Beadles"
    },
    {
        "id": 723,
        "first_name": "Dallon",
        "last_name": "Diggar"
    },
    {
        "id": 724,
        "first_name": "Kassey",
        "last_name": "Dickenson"
    },
    {
        "id": 725,
        "first_name": "Faunie",
        "last_name": "Gardiner"
    },
    {
        "id": 726,
        "first_name": "Willetta",
        "last_name": "Soigoux"
    },
    {
        "id": 727,
        "first_name": "Leslie",
        "last_name": "Baudet"
    },
    {
        "id": 728,
        "first_name": "Amargo",
        "last_name": "Quirke"
    },
    {
        "id": 729,
        "first_name": "Jaquelin",
        "last_name": "Aynold"
    },
    {
        "id": 730,
        "first_name": "Jenni",
        "last_name": "McAlpine"
    },
    {
        "id": 731,
        "first_name": "Drake",
        "last_name": "McCathie"
    },
    {
        "id": 732,
        "first_name": "Mersey",
        "last_name": "Sherrum"
    },
    {
        "id": 733,
        "first_name": "Vincenty",
        "last_name": "Triggle"
    },
    {
        "id": 734,
        "first_name": "Odella",
        "last_name": "Killingbeck"
    },
    {
        "id": 735,
        "first_name": "Rozalin",
        "last_name": "Gynn"
    },
    {
        "id": 736,
        "first_name": "Tommi",
        "last_name": "Fuchs"
    },
    {
        "id": 737,
        "first_name": "Harlie",
        "last_name": "Yourell"
    },
    {
        "id": 738,
        "first_name": "Ev",
        "last_name": "Sherlaw"
    },
    {
        "id": 739,
        "first_name": "Fawnia",
        "last_name": "Greader"
    },
    {
        "id": 740,
        "first_name": "Vernor",
        "last_name": "Dengate"
    },
    {
        "id": 741,
        "first_name": "Aryn",
        "last_name": "Munro"
    },
    {
        "id": 742,
        "first_name": "Alfred",
        "last_name": "Golder"
    },
    {
        "id": 743,
        "first_name": "Elvis",
        "last_name": "Moralas"
    },
    {
        "id": 744,
        "first_name": "Fitzgerald",
        "last_name": "Lindeboom"
    },
    {
        "id": 745,
        "first_name": "Terrijo",
        "last_name": "Crownshaw"
    },
    {
        "id": 746,
        "first_name": "Konrad",
        "last_name": "Ellerker"
    },
    {
        "id": 747,
        "first_name": "Lionello",
        "last_name": "Dugald"
    },
    {
        "id": 748,
        "first_name": "Phaidra",
        "last_name": "Clausen-Thue"
    },
    {
        "id": 749,
        "first_name": "Gardener",
        "last_name": "MacKellen"
    },
    {
        "id": 750,
        "first_name": "Montague",
        "last_name": "De Biaggi"
    },
    {
        "id": 751,
        "first_name": "Lonny",
        "last_name": "Drable"
    },
    {
        "id": 752,
        "first_name": "Shanda",
        "last_name": "Abramof"
    },
    {
        "id": 753,
        "first_name": "Benedicta",
        "last_name": "Coltherd"
    },
    {
        "id": 754,
        "first_name": "Rutger",
        "last_name": "Martusov"
    },
    {
        "id": 755,
        "first_name": "Cyndie",
        "last_name": "Colling"
    },
    {
        "id": 756,
        "first_name": "Caspar",
        "last_name": "Beldan"
    },
    {
        "id": 757,
        "first_name": "Connie",
        "last_name": "Bacup"
    },
    {
        "id": 758,
        "first_name": "Alisun",
        "last_name": "Bramhall"
    },
    {
        "id": 759,
        "first_name": "Drusy",
        "last_name": "Bonafacino"
    },
    {
        "id": 760,
        "first_name": "Correna",
        "last_name": "Matyushkin"
    },
    {
        "id": 761,
        "first_name": "Demott",
        "last_name": "Crane"
    },
    {
        "id": 762,
        "first_name": "Garnette",
        "last_name": "Sedgmond"
    },
    {
        "id": 763,
        "first_name": "Annamarie",
        "last_name": "Stidston"
    },
    {
        "id": 764,
        "first_name": "Victoria",
        "last_name": "Gheorghie"
    },
    {
        "id": 765,
        "first_name": "Cosetta",
        "last_name": "Gionettitti"
    },
    {
        "id": 766,
        "first_name": "Syman",
        "last_name": "Garfitt"
    },
    {
        "id": 767,
        "first_name": "Johnathan",
        "last_name": "Di Baudi"
    },
    {
        "id": 768,
        "first_name": "Melinda",
        "last_name": "Leyban"
    },
    {
        "id": 769,
        "first_name": "Cornelle",
        "last_name": "Kinane"
    },
    {
        "id": 770,
        "first_name": "Sadie",
        "last_name": "Debney"
    },
    {
        "id": 771,
        "first_name": "Ermentrude",
        "last_name": "Belcham"
    },
    {
        "id": 772,
        "first_name": "Curcio",
        "last_name": "Waldren"
    },
    {
        "id": 773,
        "first_name": "Eleanora",
        "last_name": "Hinckley"
    },
    {
        "id": 774,
        "first_name": "Biddy",
        "last_name": "McKeevers"
    },
    {
        "id": 775,
        "first_name": "Urbain",
        "last_name": "Busher"
    },
    {
        "id": 776,
        "first_name": "Aldrich",
        "last_name": "Monteaux"
    },
    {
        "id": 777,
        "first_name": "Johnny",
        "last_name": "Cloake"
    },
    {
        "id": 778,
        "first_name": "Colline",
        "last_name": "Wiggans"
    },
    {
        "id": 779,
        "first_name": "Marena",
        "last_name": "Lohoar"
    },
    {
        "id": 780,
        "first_name": "Therese",
        "last_name": "Wilcock"
    },
    {
        "id": 781,
        "first_name": "Ericka",
        "last_name": "Waulker"
    },
    {
        "id": 782,
        "first_name": "Bernard",
        "last_name": "Speck"
    },
    {
        "id": 783,
        "first_name": "Hernando",
        "last_name": "Tunder"
    },
    {
        "id": 784,
        "first_name": "Chandler",
        "last_name": "Ligerton"
    },
    {
        "id": 785,
        "first_name": "Adey",
        "last_name": "Vanacci"
    },
    {
        "id": 786,
        "first_name": "Jecho",
        "last_name": "Ockendon"
    },
    {
        "id": 787,
        "first_name": "Desi",
        "last_name": "Magner"
    },
    {
        "id": 788,
        "first_name": "Glennie",
        "last_name": "Mulqueen"
    },
    {
        "id": 789,
        "first_name": "Tynan",
        "last_name": "Hebbard"
    },
    {
        "id": 790,
        "first_name": "Rod",
        "last_name": "Beavers"
    },
    {
        "id": 791,
        "first_name": "Jocelin",
        "last_name": "Brocket"
    },
    {
        "id": 792,
        "first_name": "Claudie",
        "last_name": "Deveral"
    },
    {
        "id": 793,
        "first_name": "Lorelle",
        "last_name": "Tremmil"
    },
    {
        "id": 794,
        "first_name": "Baryram",
        "last_name": "MacGahy"
    },
    {
        "id": 795,
        "first_name": "Kimberley",
        "last_name": "Fellona"
    },
    {
        "id": 796,
        "first_name": "Jordanna",
        "last_name": "Belmont"
    },
    {
        "id": 797,
        "first_name": "Babb",
        "last_name": "Bendley"
    },
    {
        "id": 798,
        "first_name": "Valery",
        "last_name": "Belverstone"
    },
    {
        "id": 799,
        "first_name": "Ward",
        "last_name": "Lucock"
    },
    {
        "id": 800,
        "first_name": "Orlando",
        "last_name": "Jeste"
    },
    {
        "id": 801,
        "first_name": "Reinald",
        "last_name": "Dodwell"
    },
    {
        "id": 802,
        "first_name": "Broderic",
        "last_name": "Brown"
    },
    {
        "id": 803,
        "first_name": "Kiley",
        "last_name": "Woolpert"
    },
    {
        "id": 804,
        "first_name": "Bartel",
        "last_name": "Burtwell"
    },
    {
        "id": 805,
        "first_name": "Denice",
        "last_name": "Bree"
    },
    {
        "id": 806,
        "first_name": "Abe",
        "last_name": "Birdwistle"
    },
    {
        "id": 807,
        "first_name": "Avril",
        "last_name": "Pietzker"
    },
    {
        "id": 808,
        "first_name": "Kaylee",
        "last_name": "Jorden"
    },
    {
        "id": 809,
        "first_name": "Frazer",
        "last_name": "Emmison"
    },
    {
        "id": 810,
        "first_name": "Tirrell",
        "last_name": "Jewks"
    },
    {
        "id": 811,
        "first_name": "Neville",
        "last_name": "Giffkins"
    },
    {
        "id": 812,
        "first_name": "Rickert",
        "last_name": "Linford"
    },
    {
        "id": 813,
        "first_name": "Sibel",
        "last_name": "Deely"
    },
    {
        "id": 814,
        "first_name": "Gustie",
        "last_name": "Wilstead"
    },
    {
        "id": 815,
        "first_name": "Clemmie",
        "last_name": "Maly"
    },
    {
        "id": 816,
        "first_name": "Devland",
        "last_name": "McQuin"
    },
    {
        "id": 817,
        "first_name": "Alasteir",
        "last_name": "Chartre"
    },
    {
        "id": 818,
        "first_name": "Gloriane",
        "last_name": "Conahy"
    },
    {
        "id": 819,
        "first_name": "Neall",
        "last_name": "Phibb"
    },
    {
        "id": 820,
        "first_name": "Sianna",
        "last_name": "Wentworth"
    },
    {
        "id": 821,
        "first_name": "Shaylyn",
        "last_name": "Kiddy"
    },
    {
        "id": 822,
        "first_name": "Rickie",
        "last_name": "Wasmuth"
    },
    {
        "id": 823,
        "first_name": "Selig",
        "last_name": "Fandrey"
    },
    {
        "id": 824,
        "first_name": "Alayne",
        "last_name": "Roskruge"
    },
    {
        "id": 825,
        "first_name": "Sabina",
        "last_name": "Tabbitt"
    },
    {
        "id": 826,
        "first_name": "Wang",
        "last_name": "Sandison"
    },
    {
        "id": 827,
        "first_name": "Mamie",
        "last_name": "Shafto"
    },
    {
        "id": 828,
        "first_name": "Chelsie",
        "last_name": "Dunan"
    },
    {
        "id": 829,
        "first_name": "Artemis",
        "last_name": "Balchin"
    },
    {
        "id": 830,
        "first_name": "Giralda",
        "last_name": "Costley"
    },
    {
        "id": 831,
        "first_name": "Candida",
        "last_name": "Cadigan"
    },
    {
        "id": 832,
        "first_name": "Petronilla",
        "last_name": "Bernhardsson"
    },
    {
        "id": 833,
        "first_name": "Sergent",
        "last_name": "Duinbleton"
    },
    {
        "id": 834,
        "first_name": "Terri-jo",
        "last_name": "Scoles"
    },
    {
        "id": 835,
        "first_name": "Lainey",
        "last_name": "Leslie"
    },
    {
        "id": 836,
        "first_name": "Rodi",
        "last_name": "Mahedy"
    },
    {
        "id": 837,
        "first_name": "Bliss",
        "last_name": "Setter"
    },
    {
        "id": 838,
        "first_name": "Mariam",
        "last_name": "Pawson"
    },
    {
        "id": 839,
        "first_name": "Sheri",
        "last_name": "Datte"
    },
    {
        "id": 840,
        "first_name": "Prudi",
        "last_name": "Weerdenburg"
    },
    {
        "id": 841,
        "first_name": "Sisely",
        "last_name": "Turbill"
    },
    {
        "id": 842,
        "first_name": "Marguerite",
        "last_name": "Duff"
    },
    {
        "id": 843,
        "first_name": "Timmy",
        "last_name": "MacMearty"
    },
    {
        "id": 844,
        "first_name": "Cristobal",
        "last_name": "Allnutt"
    },
    {
        "id": 845,
        "first_name": "Suki",
        "last_name": "Bittleson"
    },
    {
        "id": 846,
        "first_name": "Meridel",
        "last_name": "Staker"
    },
    {
        "id": 847,
        "first_name": "Diarmid",
        "last_name": "Kneeshaw"
    },
    {
        "id": 848,
        "first_name": "Kasper",
        "last_name": "Cunradi"
    },
    {
        "id": 849,
        "first_name": "Cointon",
        "last_name": "Konert"
    },
    {
        "id": 850,
        "first_name": "Jan",
        "last_name": "Churches"
    },
    {
        "id": 851,
        "first_name": "Krystyna",
        "last_name": "Povey"
    },
    {
        "id": 852,
        "first_name": "Mathilde",
        "last_name": "Linton"
    },
    {
        "id": 853,
        "first_name": "Austen",
        "last_name": "Gait"
    },
    {
        "id": 854,
        "first_name": "Gradeigh",
        "last_name": "Vanlint"
    },
    {
        "id": 855,
        "first_name": "Gertrud",
        "last_name": "Sivills"
    },
    {
        "id": 856,
        "first_name": "Howey",
        "last_name": "Mildmott"
    },
    {
        "id": 857,
        "first_name": "Belinda",
        "last_name": "Ellick"
    },
    {
        "id": 858,
        "first_name": "Ike",
        "last_name": "Markovic"
    },
    {
        "id": 859,
        "first_name": "Elga",
        "last_name": "Iacovino"
    },
    {
        "id": 860,
        "first_name": "Vicky",
        "last_name": "Kondrachenko"
    },
    {
        "id": 861,
        "first_name": "Jo",
        "last_name": "Greally"
    },
    {
        "id": 862,
        "first_name": "Jake",
        "last_name": "Stembridge"
    },
    {
        "id": 863,
        "first_name": "Krisha",
        "last_name": "Simm"
    },
    {
        "id": 864,
        "first_name": "Orelee",
        "last_name": "Glasson"
    },
    {
        "id": 865,
        "first_name": "Kaia",
        "last_name": "Draye"
    },
    {
        "id": 866,
        "first_name": "Dre",
        "last_name": "Goodanew"
    },
    {
        "id": 867,
        "first_name": "Susy",
        "last_name": "Sales"
    },
    {
        "id": 868,
        "first_name": "Kylynn",
        "last_name": "Marking"
    },
    {
        "id": 869,
        "first_name": "Nathan",
        "last_name": "Smout"
    },
    {
        "id": 870,
        "first_name": "Hadlee",
        "last_name": "Rubenczyk"
    },
    {
        "id": 871,
        "first_name": "Lark",
        "last_name": "Maylott"
    },
    {
        "id": 872,
        "first_name": "Hollis",
        "last_name": "Braddock"
    },
    {
        "id": 873,
        "first_name": "Laryssa",
        "last_name": "De Lasci"
    },
    {
        "id": 874,
        "first_name": "Annamaria",
        "last_name": "Lipgens"
    },
    {
        "id": 875,
        "first_name": "Alverta",
        "last_name": "Gerrelts"
    },
    {
        "id": 876,
        "first_name": "Cassey",
        "last_name": "Faucherand"
    },
    {
        "id": 877,
        "first_name": "Delila",
        "last_name": "Titcumb"
    },
    {
        "id": 878,
        "first_name": "Ferrell",
        "last_name": "Darwent"
    },
    {
        "id": 879,
        "first_name": "Wilona",
        "last_name": "Vernalls"
    },
    {
        "id": 880,
        "first_name": "Deonne",
        "last_name": "Geary"
    },
    {
        "id": 881,
        "first_name": "Whittaker",
        "last_name": "Goodered"
    },
    {
        "id": 882,
        "first_name": "Jessamyn",
        "last_name": "Hardiker"
    },
    {
        "id": 883,
        "first_name": "Joella",
        "last_name": "von Grollmann"
    },
    {
        "id": 884,
        "first_name": "Abraham",
        "last_name": "Panichelli"
    },
    {
        "id": 885,
        "first_name": "Sansone",
        "last_name": "Reymers"
    },
    {
        "id": 886,
        "first_name": "Cly",
        "last_name": "Daville"
    },
    {
        "id": 887,
        "first_name": "Gilda",
        "last_name": "Danielli"
    },
    {
        "id": 888,
        "first_name": "Shel",
        "last_name": "Koenraad"
    },
    {
        "id": 889,
        "first_name": "Betsy",
        "last_name": "Skerrett"
    },
    {
        "id": 890,
        "first_name": "Burr",
        "last_name": "Moggach"
    },
    {
        "id": 891,
        "first_name": "Kasper",
        "last_name": "Duthie"
    },
    {
        "id": 892,
        "first_name": "Laurene",
        "last_name": "Pizzie"
    },
    {
        "id": 893,
        "first_name": "Lusa",
        "last_name": "Molyneux"
    },
    {
        "id": 894,
        "first_name": "Faustine",
        "last_name": "Danit"
    },
    {
        "id": 895,
        "first_name": "Roscoe",
        "last_name": "Bwy"
    },
    {
        "id": 896,
        "first_name": "Lizbeth",
        "last_name": "Ledward"
    },
    {
        "id": 897,
        "first_name": "Rodrigo",
        "last_name": "Seton"
    },
    {
        "id": 898,
        "first_name": "Raffaello",
        "last_name": "Earwaker"
    },
    {
        "id": 899,
        "first_name": "Riobard",
        "last_name": "Blight"
    },
    {
        "id": 900,
        "first_name": "Cynthie",
        "last_name": "Gilderoy"
    },
    {
        "id": 901,
        "first_name": "Ashlee",
        "last_name": "Bilbrey"
    },
    {
        "id": 902,
        "first_name": "Darci",
        "last_name": "Soloway"
    },
    {
        "id": 903,
        "first_name": "Wiatt",
        "last_name": "Ritmeier"
    },
    {
        "id": 904,
        "first_name": "Arnaldo",
        "last_name": "Comiskey"
    },
    {
        "id": 905,
        "first_name": "Roselin",
        "last_name": "Tungay"
    },
    {
        "id": 906,
        "first_name": "Dasie",
        "last_name": "Sutherley"
    },
    {
        "id": 907,
        "first_name": "Silas",
        "last_name": "Scully"
    },
    {
        "id": 908,
        "first_name": "Tony",
        "last_name": "Le Gallo"
    },
    {
        "id": 909,
        "first_name": "Mayer",
        "last_name": "Lanphier"
    },
    {
        "id": 910,
        "first_name": "Reggie",
        "last_name": "Vlasenko"
    },
    {
        "id": 911,
        "first_name": "Philippa",
        "last_name": "Cloney"
    },
    {
        "id": 912,
        "first_name": "Nike",
        "last_name": "Tzar"
    },
    {
        "id": 913,
        "first_name": "Joyous",
        "last_name": "Wheeldon"
    },
    {
        "id": 914,
        "first_name": "Clemmie",
        "last_name": "Zellner"
    },
    {
        "id": 915,
        "first_name": "Konstantin",
        "last_name": "Meatyard"
    },
    {
        "id": 916,
        "first_name": "Douglass",
        "last_name": "Libri"
    },
    {
        "id": 917,
        "first_name": "Marlyn",
        "last_name": "Bantick"
    },
    {
        "id": 918,
        "first_name": "Eddi",
        "last_name": "Santhouse"
    },
    {
        "id": 919,
        "first_name": "Barnebas",
        "last_name": "Saby"
    },
    {
        "id": 920,
        "first_name": "Osborn",
        "last_name": "Stratford"
    },
    {
        "id": 921,
        "first_name": "Yasmeen",
        "last_name": "Yakov"
    },
    {
        "id": 922,
        "first_name": "Christel",
        "last_name": "Gooders"
    },
    {
        "id": 923,
        "first_name": "Jenn",
        "last_name": "Budden"
    },
    {
        "id": 924,
        "first_name": "Lek",
        "last_name": "Lerhinan"
    },
    {
        "id": 925,
        "first_name": "Kelsey",
        "last_name": "Boss"
    },
    {
        "id": 926,
        "first_name": "Richard",
        "last_name": "Kyd"
    },
    {
        "id": 927,
        "first_name": "Jeannine",
        "last_name": "Fairbrace"
    },
    {
        "id": 928,
        "first_name": "Lexi",
        "last_name": "Schindler"
    },
    {
        "id": 929,
        "first_name": "Carter",
        "last_name": "Lyal"
    },
    {
        "id": 930,
        "first_name": "Kale",
        "last_name": "Cary"
    },
    {
        "id": 931,
        "first_name": "Cthrine",
        "last_name": "O' Mullane"
    },
    {
        "id": 932,
        "first_name": "Morena",
        "last_name": "Bes"
    },
    {
        "id": 933,
        "first_name": "Diana",
        "last_name": "Stickells"
    },
    {
        "id": 934,
        "first_name": "Cristabel",
        "last_name": "Maric"
    },
    {
        "id": 935,
        "first_name": "Gaylord",
        "last_name": "Brik"
    },
    {
        "id": 936,
        "first_name": "Amaleta",
        "last_name": "Challiss"
    },
    {
        "id": 937,
        "first_name": "Andriette",
        "last_name": "Bucknell"
    },
    {
        "id": 938,
        "first_name": "Xymenes",
        "last_name": "Hook"
    },
    {
        "id": 939,
        "first_name": "Nehemiah",
        "last_name": "Cathcart"
    },
    {
        "id": 940,
        "first_name": "Whittaker",
        "last_name": "Eccleshare"
    },
    {
        "id": 941,
        "first_name": "Germayne",
        "last_name": "Dutson"
    },
    {
        "id": 942,
        "first_name": "Byrann",
        "last_name": "Lehrer"
    },
    {
        "id": 943,
        "first_name": "Laurens",
        "last_name": "Hamman"
    },
    {
        "id": 944,
        "first_name": "Delia",
        "last_name": "Pinkstone"
    },
    {
        "id": 945,
        "first_name": "Andriette",
        "last_name": "Sharpless"
    },
    {
        "id": 946,
        "first_name": "Klara",
        "last_name": "Poge"
    },
    {
        "id": 947,
        "first_name": "Stafani",
        "last_name": "MacRory"
    },
    {
        "id": 948,
        "first_name": "Jackelyn",
        "last_name": "Gueste"
    },
    {
        "id": 949,
        "first_name": "Alick",
        "last_name": "Cheesley"
    },
    {
        "id": 950,
        "first_name": "Vinny",
        "last_name": "Halwood"
    },
    {
        "id": 951,
        "first_name": "Davita",
        "last_name": "Cainey"
    },
    {
        "id": 952,
        "first_name": "Jeffy",
        "last_name": "Onge"
    },
    {
        "id": 953,
        "first_name": "Nanon",
        "last_name": "Alsop"
    },
    {
        "id": 954,
        "first_name": "Cicely",
        "last_name": "Gravey"
    },
    {
        "id": 955,
        "first_name": "Benni",
        "last_name": "Salatino"
    },
    {
        "id": 956,
        "first_name": "Sonni",
        "last_name": "Tuberfield"
    },
    {
        "id": 957,
        "first_name": "Clement",
        "last_name": "Rignold"
    },
    {
        "id": 958,
        "first_name": "Joyce",
        "last_name": "Tiffin"
    },
    {
        "id": 959,
        "first_name": "Cyrille",
        "last_name": "Mairs"
    },
    {
        "id": 960,
        "first_name": "Guntar",
        "last_name": "Flaonier"
    },
    {
        "id": 961,
        "first_name": "Veronike",
        "last_name": "Lalor"
    },
    {
        "id": 962,
        "first_name": "Read",
        "last_name": "Di Napoli"
    },
    {
        "id": 963,
        "first_name": "Miguela",
        "last_name": "Nyland"
    },
    {
        "id": 964,
        "first_name": "Wilona",
        "last_name": "Shine"
    },
    {
        "id": 965,
        "first_name": "Nichole",
        "last_name": "Hamley"
    },
    {
        "id": 966,
        "first_name": "Perren",
        "last_name": "Pietruszka"
    },
    {
        "id": 967,
        "first_name": "Loria",
        "last_name": "Batson"
    },
    {
        "id": 968,
        "first_name": "Vin",
        "last_name": "Valenti"
    },
    {
        "id": 969,
        "first_name": "Adolph",
        "last_name": "Riglar"
    },
    {
        "id": 970,
        "first_name": "Ingeberg",
        "last_name": "Cornock"
    },
    {
        "id": 971,
        "first_name": "Evered",
        "last_name": "Limpkin"
    },
    {
        "id": 972,
        "first_name": "Mikkel",
        "last_name": "McGiffin"
    },
    {
        "id": 973,
        "first_name": "Demetris",
        "last_name": "Phittiplace"
    },
    {
        "id": 974,
        "first_name": "Bartlet",
        "last_name": "Inger"
    },
    {
        "id": 975,
        "first_name": "Louise",
        "last_name": "Lempertz"
    },
    {
        "id": 976,
        "first_name": "Dona",
        "last_name": "Aspland"
    },
    {
        "id": 977,
        "first_name": "Angelia",
        "last_name": "Ickowics"
    },
    {
        "id": 978,
        "first_name": "Janeta",
        "last_name": "Lissandre"
    },
    {
        "id": 979,
        "first_name": "Levy",
        "last_name": "Baleine"
    },
    {
        "id": 980,
        "first_name": "Vanya",
        "last_name": "Casse"
    },
    {
        "id": 981,
        "first_name": "Suki",
        "last_name": "Darco"
    },
    {
        "id": 982,
        "first_name": "Rudd",
        "last_name": "Gwynne"
    },
    {
        "id": 983,
        "first_name": "Bobby",
        "last_name": "Charleston"
    },
    {
        "id": 984,
        "first_name": "Mel",
        "last_name": "Hotchkin"
    },
    {
        "id": 985,
        "first_name": "Sibylla",
        "last_name": "MacNockater"
    },
    {
        "id": 986,
        "first_name": "Brenn",
        "last_name": "Abramowitch"
    },
    {
        "id": 987,
        "first_name": "Ines",
        "last_name": "Jenkyn"
    },
    {
        "id": 988,
        "first_name": "Berny",
        "last_name": "Foxworthy"
    },
    {
        "id": 989,
        "first_name": "Dannie",
        "last_name": "Robbs"
    },
    {
        "id": 990,
        "first_name": "Cross",
        "last_name": "Weeden"
    },
    {
        "id": 991,
        "first_name": "Oona",
        "last_name": "Jancey"
    },
    {
        "id": 992,
        "first_name": "Shoshana",
        "last_name": "Vigors"
    },
    {
        "id": 993,
        "first_name": "Elianore",
        "last_name": "Osband"
    },
    {
        "id": 994,
        "first_name": "Cirillo",
        "last_name": "Verlinden"
    },
    {
        "id": 995,
        "first_name": "Nevins",
        "last_name": "Boog"
    },
    {
        "id": 996,
        "first_name": "Dyana",
        "last_name": "Goldup"
    },
    {
        "id": 997,
        "first_name": "Elicia",
        "last_name": "Roelofsen"
    },
    {
        "id": 998,
        "first_name": "Cozmo",
        "last_name": "Kaesmans"
    },
    {
        "id": 999,
        "first_name": "Dacy",
        "last_name": "Sabate"
    },
    {
        "id": 1000,
        "first_name": "Morly",
        "last_name": "Gostall"
    }
]